HelpingAI/__init__.py
HelpingAI/base_models.py
HelpingAI/client.py
HelpingAI/error.py
HelpingAI/logging.py
HelpingAI/models.py
HelpingAI/py.typed
HelpingAI/version.py
HelpingAI/client/__init__.py
HelpingAI/client/base.py
HelpingAI/client/chat.py
HelpingAI/client/completions.py
HelpingAI/client/main.py
HelpingAI/tools/__init__.py
HelpingAI/tools/compatibility.py
HelpingAI/tools/core.py
HelpingAI/tools/errors.py
HelpingAI/tools/mcp_client.py
HelpingAI/tools/mcp_manager.py
HelpingAI/tools/registry.py
HelpingAI/tools/schema.py
HelpingAI/tools/builtin_tools/__init__.py
HelpingAI/tools/builtin_tools/base.py
HelpingAI/tools/builtin_tools/code_interpreter.py
HelpingAI/tools/builtin_tools/web_search.py
helpingai-1.2.4.dist-info/licenses/LICENSE
helpingai-1.2.4.dist-info/METADATA
helpingai-1.2.4.dist-info/WHEEL
helpingai-1.2.4.dist-info/top_level.txt
helpingai-1.2.4.dist-info/RECORD
