Metadata-Version: 2.4
Name: HelpingAI
Version: 1.2.4
Summary: Python client library for the HelpingAI API
Author-email: HelpingAI <Team@helpingai.co>
License: MIT
Project-URL: Homepage, https://github.com/HelpingAI/HelpingAI-python
Project-URL: Documentation, https://helpingai.co/docs
Project-URL: Source, https://github.com/HelpingAI/HelpingAI-python
Project-URL: Issues, https://github.com/HelpingAI/HelpingAI-python/issues
Keywords: ai,api,client,helpingai
Classifier: Development Status :: 5 - Production/Stable
Classifier: Intended Audience :: Developers
Classifier: License :: OSI Approved :: MIT License
Classifier: Operating System :: OS Independent
Classifier: Programming Language :: Python :: 3
Classifier: Programming Language :: Python :: 3.7
Classifier: Programming Language :: Python :: 3.8
Classifier: Programming Language :: Python :: 3.9
Classifier: Programming Language :: Python :: 3.10
Classifier: Programming Language :: Python :: 3.11
Classifier: Programming Language :: Python :: 3.12
Classifier: Programming Language :: Python :: 3.13
Classifier: Programming Language :: Python :: 3.14
Classifier: Topic :: Software Development :: Libraries :: Python Modules
Requires-Python: >=3.7
License-File: LICENSE
Requires-Dist: requests
Requires-Dist: typing_extensions
Provides-Extra: mcp
Requires-Dist: mcp>=1.0.0; extra == "mcp"
Provides-Extra: dev
Requires-Dist: pytest; extra == "dev"
Requires-Dist: pytest-cov; extra == "dev"
Dynamic: license-file
